odoo/addons/account_operating_unit/README.rst
odoo/addons/account_operating_unit/__init__.py
odoo/addons/account_operating_unit/__manifest__.py
odoo/addons/account_operating_unit/i18n/account_operating_unit.pot
odoo/addons/account_operating_unit/i18n/es_MX.po
odoo/addons/account_operating_unit/i18n/it.po
odoo/addons/account_operating_unit/models/__init__.py
odoo/addons/account_operating_unit/models/account_bank_statement.py
odoo/addons/account_operating_unit/models/account_journal.py
odoo/addons/account_operating_unit/models/account_move.py
odoo/addons/account_operating_unit/models/account_partial_reconcile.py
odoo/addons/account_operating_unit/models/account_payment.py
odoo/addons/account_operating_unit/models/res_company.py
odoo/addons/account_operating_unit/readme/CONFIGURE.md
odoo/addons/account_operating_unit/readme/CONTRIBUTORS.md
odoo/addons/account_operating_unit/readme/DESCRIPTION.md
odoo/addons/account_operating_unit/readme/ROADMAP.md
odoo/addons/account_operating_unit/readme/USAGE.md
odoo/addons/account_operating_unit/report/__init__.py
odoo/addons/account_operating_unit/report/account_invoice_report.py
odoo/addons/account_operating_unit/security/account_security.xml
odoo/addons/account_operating_unit/static/description/icon.png
odoo/addons/account_operating_unit/static/description/index.html
odoo/addons/account_operating_unit/tests/__init__.py
odoo/addons/account_operating_unit/tests/test_account_operating_unit.py
odoo/addons/account_operating_unit/tests/test_account_reconcile.py
odoo/addons/account_operating_unit/tests/test_cross_ou_journal_entry.py
odoo/addons/account_operating_unit/tests/test_invoice_operating_unit.py
odoo/addons/account_operating_unit/tests/test_operating_unit_security.py
odoo/addons/account_operating_unit/tests/test_payment_operating_unit.py
odoo/addons/account_operating_unit/views/account_invoice_report_view.xml
odoo/addons/account_operating_unit/views/account_journal_view.xml
odoo_addon_account_operating_unit-19.0.1.0.1.dist-info/METADATA
odoo_addon_account_operating_unit-19.0.1.0.1.dist-info/WHEEL
odoo_addon_account_operating_unit-19.0.1.0.1.dist-info/top_level.txt
odoo_addon_account_operating_unit-19.0.1.0.1.dist-info/RECORD
