Metadata-Version: 2.1
Name: odoo-addon-account_operating_unit
Version: 19.0.1.0.1
Requires-Dist: odoo-addon-analytic_operating_unit==19.0.*
Requires-Dist: odoo-addon-base_view_inheritance_extension==19.0.*
Requires-Dist: odoo==19.0.*
Summary: Introduces Operating Unit (OU) in invoices and Accounting Entries with clearing account
Home-page: https://github.com/OCA/operating-unit
License: LGPL-3
Author: ForgeFlow, Serpent Consulting Services Pvt. Ltd.,WilldooIT Pty Ltd,Odoo Community Association (OCA)
Author-email: support@odoo-community.org
Classifier: Programming Language :: Python
Classifier: Framework :: Odoo
Classifier: Framework :: Odoo :: 19.0
Classifier: License :: OSI Approved :: GNU Lesser General Public License v3 (LGPLv3)
